README.md
nautobot_ansible_filters/__init__.py
nautobot_ansible_filters/jinja_filters.py
nautobot_ansible_filters/tests/__init__.py
nautobot_ansible_filters/tests/test_app_config.py
nautobot_ansible_filters/utilities.py
nautobot_ansible_filters-2.0.2.dist-info/METADATA
nautobot_ansible_filters-2.0.2.dist-info/WHEEL
nautobot_ansible_filters-2.0.2.dist-info/RECORD
