Metadata-Version: 2.1
Name: nautobot-ansible-filters
Version: 2.0.2
Summary: Nautobot App that provides Ansible filters within Nautobot.
Home-page: https://github.com/FragmentedPacket/nautobot-plugin-ansible-filters
Keywords: nautobot,nautobot-plugin
Author: Mikhail Yohman
Author-email: mikhail.yohman@gmail.com
Requires-Python: >=3.8,<3.12
Classifier: Programming Language :: Python :: 3
Classifier: Programming Language :: Python :: 3.8
Classifier: Programming Language :: Python :: 3.9
Classifier: Programming Language :: Python :: 3.10
Classifier: Programming Language :: Python :: 3.11
Provides-Extra: nautobot
Requires-Dist: importlib-metadata (>=4,<5) ; python_version < "3.10"
Requires-Dist: jinja2-ansible-filters (>=1.3,<2.0)
Requires-Dist: nautobot (>=1.2,<3.0) ; extra == "nautobot"
Project-URL: Repository, https://github.com/FragmentedPacket/nautobot-plugin-ansible-filters
